xchanger_suite_integration/__init__.py
xchanger_suite_integration/xchanger_suite_integration.py
xchanger_suite_integration-0.1.dist-info/LICENSE
xchanger_suite_integration-0.1.dist-info/METADATA
xchanger_suite_integration-0.1.dist-info/WHEEL
xchanger_suite_integration-0.1.dist-info/top_level.txt
xchanger_suite_integration-0.1.dist-info/RECORD
