Metadata-Version: 2.1
Name: xchanger-suite-integration
Version: 0.1
Summary: This package facilitates integrating Xchanger Suite capabilities with applications using Python
Home-page: https://github.com/natewkidd/xchanger_suite_integration
Author: Nathan W. Kidd
Author-email: nathan.kidd@htri.net
License: MIT
Platform: UNKNOWN
Classifier: Programming Language :: Python :: 3
Classifier: License :: OSI Approved :: MIT License
Classifier: Operating System :: OS Independent
Requires-Python: >=3.6
